pykwalifire/__init__.py
pykwalifire/cli.py
pykwalifire/compat.py
pykwalifire/core.py
pykwalifire/errors.py
pykwalifire/rule.py
pykwalifire/types.py
pykwalifire-2.0.1.dist-info/DESCRIPTION.rst
pykwalifire-2.0.1.dist-info/METADATA
pykwalifire-2.0.1.dist-info/RECORD
pykwalifire-2.0.1.dist-info/WHEEL
pykwalifire-2.0.1.dist-info/entry_points.txt
pykwalifire-2.0.1.dist-info/metadata.json
pykwalifire-2.0.1.dist-info/top_level.txt
