Metadata-Version: 2.0
Name: pykwalifire
Version: 2.0.1
Summary: Python lib/cli for JSON/YAML schema validation, fork of pykwalify with added features
Home-page: http://github.com/sdruskat/pykwalifire
Author: Stephan Druskat
Author-email: mail@sdruskat.net
License: MIT
Platform: UNKNOWN
Classifier: Development Status :: 5 - Production/Stable
Classifier: Intended Audience :: Science/Research
Classifier: Intended Audience :: Developers
Classifier: Intended Audience :: Information Technology
Classifier: Operating System :: OS Independent
Classifier: License :: OSI Approved :: MIT License
Classifier: Environment :: Console
Classifier: Programming Language :: Python
Classifier: Programming Language :: Python :: 3
Classifier: Programming Language :: Python :: 3.3
Classifier: Programming Language :: Python :: 3.4
Classifier: Programming Language :: Python :: 3.5
Classifier: Programming Language :: Python :: 3.6
Requires-Dist: ruamel.yaml (<0.12.0,>=0.11.0)
Requires-Dist: docopt (>=0.6.2)
Requires-Dist: PyYAML (>=3.11)
Requires-Dist: python-dateutil (>=2.4.2)
